[{"customerName":"LaxmiNarayana","service":{"names":["Flight Tickets","Extra Baggage","Tax"],"prices":["10000","1500","800"]},"amount":"12300.00","upiID":"9505718154@ybl","orderID":1662637022287,"OTP":543218},{"customerName":"LaxmiNarayana","service":{"names":["Flight Tickets","Extra Baggage","Tax"],"prices":["10000","1500","800"]},"amount":"12300.00","upiID":"9505718154@ybl","orderID":1662637103806,"OTP":868453},{"customerName":"LaxmiNarayana","service":{"names":["Flight Tickets","Extra Baggage","Tax"],"prices":["10000","1500","800"]},"amount":"12300.00","upiID":"9505718154@ybl","orderID":1662637125794,"OTP":530986},{"customerName":"LaxmiNarayana","service":{"names":["Flight Tickets","Extra Baggage","Tax"],"prices":["10000","1500","800"]},"amount":"12300.00","upiID":"9505718154@ybl","orderID":1662637412032,"OTP":307549},{"customerName":"LaxmiNarayana","service":{"names":["Flight Tickets","Extra Baggage","Tax"],"prices":["10000","1500","800"]},"amount":"12300.00","upiID":"9505718154@ybl","orderID":1662637419967,"OTP":998960}]